lowatt_collect.py
lowatt_collect-1.1.dist-info/COPYING
lowatt_collect-1.1.dist-info/METADATA
lowatt_collect-1.1.dist-info/WHEEL
lowatt_collect-1.1.dist-info/entry_points.txt
lowatt_collect-1.1.dist-info/top_level.txt
lowatt_collect-1.1.dist-info/RECORD
