Metadata-Version: 2.1
Name: lowatt-collect
Version: 1.1
Summary: collect arbitrary data
Home-page: https://github.com/lowatt/lowatt_collect
Author: Sylvain Thénault
Author-email: info@lowatt.fr
License: GPL3
Platform: UNKNOWN
Classifier: Programming Language :: Python :: 3.6
Classifier: License :: OSI Approved :: GNU General Public License v3 or later (GPLv3+)
Classifier: Operating System :: OS Independent
Classifier: Topic :: System :: Archiving :: Mirroring
Requires-Dist: colorlog
Requires-Dist: pyyaml
